examples/add_domain.py
examples/add_url.py
examples/create_client.py
examples/create_client_with_timeout.py
examples/delete_domain.py
examples/delete_url.py
examples/get_filtering_rules.py
examples/get_sdk_version.py
examples/get_status.py
pyproxy_sdk/__init__.py
pyproxy_sdk/client.py
pyproxy_sdk/exceptions.py
pyproxytools_sdk-0.1.2.dist-info/licenses/LICENSE
tests/test_client.py
pyproxytools_sdk-0.1.2.dist-info/METADATA
pyproxytools_sdk-0.1.2.dist-info/WHEEL
pyproxytools_sdk-0.1.2.dist-info/top_level.txt
pyproxytools_sdk-0.1.2.dist-info/RECORD
