Metadata-Version: 2.4
Name: pyproxytools-sdk
Version: 0.1.2
Summary: Python API Client for PyProxy
Author: pyproxytools
License-Expression: MIT
Project-URL: Documentation, https://github.com/pyproxytools/pyproxy/wiki
Project-URL: Issue tracker, https://github.com/pyproxytools/pyproxy/issues
Classifier: Development Status :: 5 - Production/Stable
Classifier: Intended Audience :: Developers
Classifier: Natural Language :: English
Classifier: Operating System :: OS Independent
Classifier: Programming Language :: Python :: 3.8
Classifier: Programming Language :: Python :: 3.9
Classifier: Programming Language :: Python :: 3.10
Classifier: Programming Language :: Python :: 3.11
Classifier: Programming Language :: Python :: 3.12
Classifier: Topic :: Internet
Classifier: Topic :: Software Development :: Libraries
Classifier: Topic :: Software Development :: Libraries :: Python Modules
Classifier: Topic :: Utilities
Classifier: Typing :: Typed
License-File: LICENSE
Requires-Dist: requests>=2.31.0
Dynamic: license-file
